.hgignore
LICENSE
setup.py
wallclock.py
samples/automatic
samples/manual
wallclock.egg-info/PKG-INFO
wallclock.egg-info/SOURCES.txt
wallclock.egg-info/dependency_links.txt
wallclock.egg-info/requires.txt
wallclock.egg-info/top_level.txt