Metadata-Version: 1.0
Name: wallclock
Version: 1.0
Summary: A simple stack-based performance logger
Home-page: http://bitbucket.org/ojacobson/wallclock
Author: Owen Jacobson
Author-email: owen.jacobson@grimoire.ca
License: MIT License
Platform: UNKNOWN
Classifier: Intended Audience :: Developers
Classifier: Intended Audience :: System Administrators
Classifier: License :: OSI Approved :: MIT License
Classifier: Operating System :: OS Independent
Classifier: Topic :: Software Development :: Debuggers
Classifier: Topic :: System :: Logging
